{"export_file_version": 2, "policy_list_original": [{"policyId": "fc79e312-9fb0-4092-b7a1-7c52f824e663", "name": "[Customized] Azure-VM-resource-20 core", "policyType": "config", "policySubTypes": ["run"], "systemDefault": false, "description": "Azure VM \u8cc7\u6e90\u7b26\u5408 20 core", "severity": "high", "rule": {"name": "[Customized] Azure-VM-resource-20 core", "criteria": "00877d96-25be-4134-ada9-6fa5e98094df", "parameters": {"withIac": "false", "savedSearch": "true"}, "type": "Config"}, "recommendation": "", "cloudType": "azure", "labels": [], "enabled": false, "createdOn": 1666377159136, "createdBy": "Ediosn Yang", "lastModifiedOn": 1683738390395, "lastModifiedBy": "Bill Ho", "ruleLastModifiedOn": 1666377159136, "deleted": false, "findingTypes": [], "owner": "Wistron Corporation - 6631583873290981263", "policyMode": "custom", "policyCategory": "risk", "policyClass": "exposure", "remediable": false}, {"policyId": "156fc109-bf19-49dc-adc7-3d0ec5469c88", "name": "[Customized] Azure-VM-resource-32 core", "policyType": "config", "policySubTypes": ["run"], "systemDefault": false, "description": "Azure VM \u8cc7\u6e90\u7b26\u5408 32 core", "severity": "high", "rule": {"name": "[Customized] Azure-VM-resource-32 core", "criteria": "d583bad2-d755-4aa5-a046-1b4e4f3a6520", "parameters": {"withIac": "false", "savedSearch": "true"}, "type": "Config"}, "recommendation": "", "cloudType": "azure", "labels": [], "enabled": false, "createdOn": 1666377220927, "createdBy": "Ediosn Yang", "lastModifiedOn": 1683740422613, "lastModifiedBy": "Bill Ho", "ruleLastModifiedOn": 1666377220927, "deleted": false, "findingTypes": [], "owner": "Wistron Corporation - 6631583873290981263", "policyMode": "custom", "policyCategory": "risk", "policyClass": "exposure", "remediable": false}, {"policyId": "ec2aafe2-5c14-4bbc-9641-1c31a17c6cc5", "name": "[Customized] Azure-VM-resource-16 core", "policyType": "config", "policySubTypes": ["run"], "systemDefault": false, "description": "Azure VM \u8cc7\u6e90\u7b26\u5408 16 core", "severity": "high", "rule": {"name": "[Customized] Azure-VM-resource-16 core", "criteria": "c544d8dd-1b83-45c4-9bcb-1d6547d14e7a", "parameters": {"withIac": "false", "savedSearch": "true"}, "type": "Config"}, "recommendation": "", "cloudType": "azure", "labels": [], "enabled": false, "createdOn": 1666377020209, "createdBy": "Ediosn Yang", "lastModifiedOn": 1683741113789, "lastModifiedBy": "Bill Ho", "ruleLastModifiedOn": 1666377020209, "deleted": false, "findingTypes": [], "owner": "Wistron Corporation - 6631583873290981263", "policyMode": "custom", "policyCategory": "risk", "policyClass": "exposure", "remediable": false}, {"policyId": "4b357a61-e238-4ebc-a650-6510079c1a80", "name": "[Customized] Azure-VM-resource-48 core up", "policyType": "config", "policySubTypes": ["run"], "systemDefault": false, "description": "Azure VM \u8cc7\u6e90\u5927\u65bc\u7b49\u65bc 48 core", "severity": "high", "rule": {"name": "[Customized] Azure-VM-resource-48 core up", "criteria": "89e59b1c-65e1-4773-a3e2-4f0668100f73", "parameters": {"withIac": "false", "savedSearch": "true"}, "type": "Config"}, "recommendation": "", "cloudType": "azure", "labels": [], "enabled": false, "createdOn": 1666377337450, "createdBy": "Ediosn Yang", "lastModifiedOn": 1683741147060, "lastModifiedBy": "Bill Ho", "ruleLastModifiedOn": 1666377337450, "deleted": false, "findingTypes": [], "owner": "Wistron Corporation - 6631583873290981263", "policyMode": "custom", "policyCategory": "risk", "policyClass": "exposure", "remediable": false}], "policy_object_original": {"ec2aafe2-5c14-4bbc-9641-1c31a17c6cc5": {"policyId": "ec2aafe2-5c14-4bbc-9641-1c31a17c6cc5", "name": "[Customized] Azure-VM-resource-16 core", "policyType": "config", "policySubTypes": ["run"], "systemDefault": false, "description": "Azure VM \u8cc7\u6e90\u7b26\u5408 16 core", "severity": "high", "rule": {"name": "[Customized] Azure-VM-resource-16 core", "criteria": "c544d8dd-1b83-45c4-9bcb-1d6547d14e7a", "parameters": {"withIac": "false", "savedSearch": "true"}, "type": "Config"}, "recommendation": "", "cloudType": "azure", "complianceMetadata": [], "labels": [], "enabled": false, "createdOn": 1666377020209, "createdBy": "Ediosn Yang", "lastModifiedOn": 1683741113789, "lastModifiedBy": "Bill Ho", "ruleLastModifiedOn": 1666377020209, "deleted": false, "findingTypes": [], "owner": "Wistron Corporation - 6631583873290981263", "policyMode": "custom", "policyCategory": "risk", "policyClass": "exposure", "remediable": false}, "fc79e312-9fb0-4092-b7a1-7c52f824e663": {"policyId": "fc79e312-9fb0-4092-b7a1-7c52f824e663", "name": "[Customized] Azure-VM-resource-20 core", "policyType": "config", "policySubTypes": ["run"], "systemDefault": false, "description": "Azure VM \u8cc7\u6e90\u7b26\u5408 20 core", "severity": "high", "rule": {"name": "[Customized] Azure-VM-resource-20 core", "criteria": "00877d96-25be-4134-ada9-6fa5e98094df", "parameters": {"withIac": "false", "savedSearch": "true"}, "type": "Config"}, "recommendation": "", "cloudType": "azure", "complianceMetadata": [], "labels": [], "enabled": false, "createdOn": 1666377159136, "createdBy": "Ediosn Yang", "lastModifiedOn": 1683738390395, "lastModifiedBy": "Bill Ho", "ruleLastModifiedOn": 1666377159136, "deleted": false, "findingTypes": [], "owner": "Wistron Corporation - 6631583873290981263", "policyMode": "custom", "policyCategory": "risk", "policyClass": "exposure", "remediable": false}, "4b357a61-e238-4ebc-a650-6510079c1a80": {"policyId": "4b357a61-e238-4ebc-a650-6510079c1a80", "name": "[Customized] Azure-VM-resource-48 core up", "policyType": "config", "policySubTypes": ["run"], "systemDefault": false, "description": "Azure VM \u8cc7\u6e90\u5927\u65bc\u7b49\u65bc 48 core", "severity": "high", "rule": {"name": "[Customized] Azure-VM-resource-48 core up", "criteria": "89e59b1c-65e1-4773-a3e2-4f0668100f73", "parameters": {"withIac": "false", "savedSearch": "true"}, "type": "Config"}, "recommendation": "", "cloudType": "azure", "complianceMetadata": [], "labels": [], "enabled": false, "createdOn": 1666377337450, "createdBy": "Ediosn Yang", "lastModifiedOn": 1683741147060, "lastModifiedBy": "Bill Ho", "ruleLastModifiedOn": 1666377337450, "deleted": false, "findingTypes": [], "owner": "Wistron Corporation - 6631583873290981263", "policyMode": "custom", "policyCategory": "risk", "policyClass": "exposure", "remediable": false}, "156fc109-bf19-49dc-adc7-3d0ec5469c88": {"policyId": "156fc109-bf19-49dc-adc7-3d0ec5469c88", "name": "[Customized] Azure-VM-resource-32 core", "policyType": "config", "policySubTypes": ["run"], "systemDefault": false, "description": "Azure VM \u8cc7\u6e90\u7b26\u5408 32 core", "severity": "high", "rule": {"name": "[Customized] Azure-VM-resource-32 core", "criteria": "d583bad2-d755-4aa5-a046-1b4e4f3a6520", "parameters": {"withIac": "false", "savedSearch": "true"}, "type": "Config"}, "recommendation": "", "cloudType": "azure", "complianceMetadata": [], "labels": [], "enabled": false, "createdOn": 1666377220927, "createdBy": "Ediosn Yang", "lastModifiedOn": 1683740422613, "lastModifiedBy": "Bill Ho", "ruleLastModifiedOn": 1666377220927, "deleted": false, "findingTypes": [], "owner": "Wistron Corporation - 6631583873290981263", "policyMode": "custom", "policyCategory": "risk", "policyClass": "exposure", "remediable": false}}, "search_object_original": {"89e59b1c-65e1-4773-a3e2-4f0668100f73": {"cloudType": "azure", "id": "89e59b1c-65e1-4773-a3e2-4f0668100f73", "name": "Azure_VM_48core_up", "description": "", "searchType": "config", "saved": true, "timeRange": {"type": "to_now", "value": "login"}, "query": "config from cloud.resource where api.name = 'azure-vm-list' AND json.rule = (['properties.hardwareProfile'].vmSize equals \"Standard_D48_v3\" or ['properties.hardwareProfile'].vmSize equals \"Standard_D64_v3\" or ['properties.hardwareProfile'].vmSize equals \"Standard_E48_v3\" or ['properties.hardwareProfile'].vmSize equals \"Standard_E64_v3\") "}, "d583bad2-d755-4aa5-a046-1b4e4f3a6520": {"cloudType": "azure", "id": "d583bad2-d755-4aa5-a046-1b4e4f3a6520", "name": "Azure_VM_32core", "description": "", "searchType": "config", "saved": true, "timeRange": {"type": "to_now", "value": "login"}, "query": "config from cloud.resource where api.name = 'azure-vm-list' AND json.rule = (['properties.hardwareProfile'].vmSize equals \"Standard_D32_v3\" or ['properties.hardwareProfile'].vmSize equals \"Standard_E32_v3\" or ['properties.hardwareProfile'].vmSize equals \"Standard_G5\") "}, "00877d96-25be-4134-ada9-6fa5e98094df": {"cloudType": "azure", "id": "00877d96-25be-4134-ada9-6fa5e98094df", "name": "Azure_VM_20core", "description": "", "searchType": "config", "saved": true, "timeRange": {"type": "to_now", "value": "login"}, "query": "config from cloud.resource where api.name = 'azure-vm-list' AND json.rule = ['properties.hardwareProfile'].vmSize equals \"Standard_D15_v2\" "}, "c544d8dd-1b83-45c4-9bcb-1d6547d14e7a": {"cloudType": "azure", "id": "c544d8dd-1b83-45c4-9bcb-1d6547d14e7a", "name": "Azure_VM_16core", "description": "", "searchType": "config", "saved": true, "timeRange": {"type": "to_now", "value": "login"}, "query": "config from cloud.resource where api.name = 'azure-vm-list' AND json.rule = ( ['properties.hardwareProfile'].vmSize equals \"A9\" or ['properties.hardwareProfile'].vmSize equals \"A11\" or ['properties.hardwareProfile'].vmSize equals \"Standard_D14\" or ['properties.hardwareProfile'].vmSize equals \"Standard_D5_v2\" or ['properties.hardwareProfile'].vmSize equals \"Standard_D14_v2\" or ['properties.hardwareProfile'].vmSize equals \"Standard_D16_v3\" or ['properties.hardwareProfile'].vmSize equals \"Standard_E16_v3\" or ['properties.hardwareProfile'].vmSize equals \"Standard_G4\" or ['properties.hardwareProfile'].vmSize equals \"Standard_H16m\" or ['properties.hardwareProfile'].vmSize equals \"Standard_H16r\" or ['properties.hardwareProfile'].vmSize equals \"Standard_H16mr\")"}}}